securicad/vanguard/__init__.py
securicad/vanguard/client.py
securicad/vanguard/exceptions.py
securicad/vanguard/py.typed
securicad_vanguard-1.0.0.dist-info/LICENSE
securicad_vanguard-1.0.0.dist-info/METADATA
securicad_vanguard-1.0.0.dist-info/NOTICE
securicad_vanguard-1.0.0.dist-info/WHEEL
securicad_vanguard-1.0.0.dist-info/top_level.txt
securicad_vanguard-1.0.0.dist-info/RECORD
