Metadata-Version: 2.1
Name: securicad-vanguard
Version: 1.0.0
Summary: A Python SDK for foreseeti's securiCAD Vanguard
Home-page: https://github.com/foreseeti/securicad-vanguard-sdk
Author: Foreseeti AB
Author-email: tech@foreseeti.com
License: The Apache Software License, Version 2.0
Keywords: securicad,vanguard,threat,modeling
Platform: UNKNOWN
Classifier: Intended Audience :: Developers
Classifier: Intended Audience :: Information Technology
Classifier: License :: OSI Approved
Classifier: License :: OSI Approved :: Apache Software License
Classifier: Natural Language :: English
Classifier: Operating System :: OS Independent
Classifier: Programming Language :: Python
Classifier: Programming Language :: Python :: 3
Classifier: Programming Language :: Python :: 3 :: Only
Classifier: Programming Language :: Python :: 3.8
Classifier: Programming Language :: Python :: 3.9
Classifier: Programming Language :: Python :: 3.10
Classifier: Topic :: Security
Classifier: Topic :: Software Development
Classifier: Topic :: Software Development :: Libraries
Classifier: Topic :: Software Development :: Libraries :: Application Frameworks
Classifier: Topic :: Software Development :: Libraries :: Python Modules
Classifier: Typing :: Typed
Requires-Python: >=3.8
License-File: LICENSE
License-File: NOTICE
Requires-Dist: beautifulsoup4
Requires-Dist: boto3
Requires-Dist: botocore
Requires-Dist: pycognito
Requires-Dist: requests
Requires-Dist: securicad-model (<2.0.0,>=1.0.0)
Provides-Extra: dev
Requires-Dist: black ; extra == 'dev'
Requires-Dist: boto3-stubs[cognito-idp] ; extra == 'dev'
Requires-Dist: build ; extra == 'dev'
Requires-Dist: isort ; extra == 'dev'
Requires-Dist: mypy ; extra == 'dev'
Requires-Dist: pylint ; extra == 'dev'
Requires-Dist: twine ; extra == 'dev'
Requires-Dist: types-beautifulsoup4 ; extra == 'dev'
Requires-Dist: types-requests ; extra == 'dev'
